CDSupdate/__CDSUParams.py
CDSupdate/__CVarsParams.py
CDSupdate/__curses_doc.py
CDSupdate/__doc.py
CDSupdate/__exceptions.py
CDSupdate/__exec.py
CDSupdate/__extracvars.py
CDSupdate/__init__.py
CDSupdate/__io.py
CDSupdate/__release.py
CDSupdate/data/ERA5-dptas-description.txt
CDSupdate/data/ERA5-name.csv
CDSupdate/data/ERA5-orog-description.txt
CDSupdate/data/ERA5-pr-description.txt
CDSupdate/data/ERA5-ps-description.txt
CDSupdate/data/ERA5-psl-description.txt
CDSupdate/data/ERA5-rlds-description.txt
CDSupdate/data/ERA5-rsds-description.txt
CDSupdate/data/ERA5-ta-description.txt
CDSupdate/data/ERA5-tas-description.txt
CDSupdate/data/ERA5-uas-description.txt
CDSupdate/data/ERA5-vas-description.txt
CDSupdate/data/ERA5-zg-description.txt
CDSupdate/data/__init__.py
CDSupdate/data/areas.csv
CDSupdate-2.3.1.data/scripts/cdsupdate
CDSupdate-2.3.1.dist-info/LICENSE
CDSupdate-2.3.1.dist-info/METADATA
CDSupdate-2.3.1.dist-info/WHEEL
CDSupdate-2.3.1.dist-info/top_level.txt
CDSupdate-2.3.1.dist-info/RECORD
