Metadata-Version: 2.1
Name: CDSupdate
Version: 2.3.1
Summary: Auto-updater of data from the Climate Data Store
Home-page: https://github.com/yrobink/CDSupdate
Author: Yoann Robin, Andreia Hisi
Author-email: yoann.robin.k@gmail.com, andreia.hisi@lsce.ipsl.fr
License: GNU-GPL3
Keywords: Climate Data Store,Auto update
Platform: linux
Platform: macosx
Platform: windows
Classifier: Development Status :: 5 - Production/Stable
Classifier: License :: OSI Approved :: GNU General Public License v3 or later (GPLv3+)
Classifier: Natural Language :: English
Classifier: Operating System :: MacOS :: MacOS X
Classifier: Operating System :: POSIX :: Linux
Classifier: Programming Language :: Python :: 3
Classifier: Topic :: Scientific/Engineering :: Mathematics
License-File: LICENSE
Requires-Dist: numpy
Requires-Dist: pandas
Requires-Dist: xarray
Requires-Dist: netCDF4
Requires-Dist: cftime
Requires-Dist: cdsapi
